cotengra/.gitattributes
cotengra/__init__.py
cotengra/_version.py
cotengra/contract.py
cotengra/core.py
cotengra/core_multi.py
cotengra/hypergraph.py
cotengra/interface.py
cotengra/oe.py
cotengra/parallel.py
cotengra/plot.py
cotengra/presets.py
cotengra/reusable.py
cotengra/schematic.py
cotengra/scoring.py
cotengra/slicer.py
cotengra/utils.py
cotengra/experimental/__init__.py
cotengra/experimental/path_compressed_branchbound.py
cotengra/experimental/path_compressed_mcts.py
cotengra/hyperoptimizers/__init__.py
cotengra/hyperoptimizers/hyper.py
cotengra/hyperoptimizers/hyper_baytune.py
cotengra/hyperoptimizers/hyper_choco.py
cotengra/hyperoptimizers/hyper_cmaes.py
cotengra/hyperoptimizers/hyper_nevergrad.py
cotengra/hyperoptimizers/hyper_optuna.py
cotengra/hyperoptimizers/hyper_random.py
cotengra/hyperoptimizers/hyper_skopt.py
cotengra/pathfinders/__init__.py
cotengra/pathfinders/path_basic.py
cotengra/pathfinders/path_compressed.py
cotengra/pathfinders/path_compressed_greedy.py
cotengra/pathfinders/path_edgesort.py
cotengra/pathfinders/path_flowcutter.py
cotengra/pathfinders/path_greedy.py
cotengra/pathfinders/path_igraph.py
cotengra/pathfinders/path_kahypar.py
cotengra/pathfinders/path_labels.py
cotengra/pathfinders/path_quickbb.py
cotengra/pathfinders/path_random.py
cotengra/pathfinders/path_simulated_annealing.py
cotengra/pathfinders/treedecomp.py
cotengra/pathfinders/kahypar_profiles/cut_kKaHyPar_sea20.ini
cotengra/pathfinders/kahypar_profiles/cut_rKaHyPar_sea20.ini
cotengra/pathfinders/kahypar_profiles/km1_kKaHyPar_sea20.ini
cotengra/pathfinders/kahypar_profiles/km1_rKaHyPar_sea20.ini
cotengra/pathfinders/kahypar_profiles/old/cut_kKaHyPar_sea20.ini
cotengra/pathfinders/kahypar_profiles/old/cut_rKaHyPar_sea20.ini
cotengra/pathfinders/kahypar_profiles/old/km1_kKaHyPar_sea20.ini
cotengra/pathfinders/kahypar_profiles/old/km1_rKaHyPar_sea20.ini
cotengra-0.7.4.dist-info/METADATA
cotengra-0.7.4.dist-info/WHEEL
cotengra-0.7.4.dist-info/licenses/LICENSE.md
cotengra-0.7.4.dist-info/RECORD
