Metadata-Version: 2.4
Name: cotengra
Version: 0.7.4
Summary: Hyper optimized contraction trees for large tensor networks and einsums.
Project-URL: Documentation, https://cotengra.readthedocs.io/
Project-URL: Repository, https://github.com/jcmgray/cotengra/
Project-URL: Issues, https://github.com/jcmgray/cotengra/issues
Project-URL: Changelog, https://cotengra.readthedocs.io/en/latest/changelog.html
Author-email: Johnnie Gray <johnniemcgray@gmail.com>
License: 
License-File: LICENSE.md
Keywords: contraction,einsum,graph,hypergraph,network,partition,tensor
Classifier: Development Status :: 3 - Alpha
Classifier: Intended Audience :: Science/Research
Classifier: License :: OSI Approved :: Apache Software License
Classifier: Operating System :: OS Independent
Classifier: Programming Language :: Python
Classifier: Programming Language :: Python :: 3.8
Classifier: Programming Language :: Python :: 3.9
Classifier: Programming Language :: Python :: 3.10
Classifier: Programming Language :: Python :: 3.11
Classifier: Programming Language :: Python :: 3.12
Classifier: Topic :: Scientific/Engineering
Requires-Python: >=3.8
Requires-Dist: autoray
Provides-Extra: docs
Requires-Dist: astroid<3.0.0; extra == 'docs'
Requires-Dist: furo; extra == 'docs'
Requires-Dist: ipython!=8.7.0; extra == 'docs'
Requires-Dist: myst-nb; extra == 'docs'
Requires-Dist: setuptools-scm; extra == 'docs'
Requires-Dist: sphinx-autoapi; extra == 'docs'
Requires-Dist: sphinx-copybutton; extra == 'docs'
Requires-Dist: sphinx-design; extra == 'docs'
Requires-Dist: sphinx>=2.0; extra == 'docs'
Provides-Extra: recommended
Requires-Dist: cmaes; extra == 'recommended'
Requires-Dist: cotengrust>=0.1.3; extra == 'recommended'
Requires-Dist: cytoolz; extra == 'recommended'
Requires-Dist: kahypar; extra == 'recommended'
Requires-Dist: networkx; extra == 'recommended'
Requires-Dist: numpy; extra == 'recommended'
Requires-Dist: opt-einsum; extra == 'recommended'
Requires-Dist: optuna; extra == 'recommended'
Requires-Dist: ray; extra == 'recommended'
Requires-Dist: tqdm; extra == 'recommended'
Provides-Extra: test
Requires-Dist: altair; extra == 'test'
Requires-Dist: baytune; extra == 'test'
Requires-Dist: chocolate; extra == 'test'
Requires-Dist: cmaes; extra == 'test'
Requires-Dist: dask; extra == 'test'
Requires-Dist: distributed; extra == 'test'
Requires-Dist: kahypar; extra == 'test'
Requires-Dist: matplotlib; extra == 'test'
Requires-Dist: networkx; extra == 'test'
Requires-Dist: nevergrad; extra == 'test'
Requires-Dist: numpy; extra == 'test'
Requires-Dist: opt-einsum; extra == 'test'
Requires-Dist: pytest; extra == 'test'
Requires-Dist: scikit-optimize; extra == 'test'
Requires-Dist: seaborn; extra == 'test'
